ember_mug/__init__.py
ember_mug/__main__.py
ember_mug/consts.py
ember_mug/data.py
ember_mug/formatting.py
ember_mug/mug.py
ember_mug/scanner.py
ember_mug/utils.py
ember_mug/cli/__init__.py
ember_mug/cli/commands.py
ember_mug/cli/helpers.py
python_ember_mug-1.2.0.dist-info/METADATA
python_ember_mug-1.2.0.dist-info/WHEEL
python_ember_mug-1.2.0.dist-info/entry_points.txt
python_ember_mug-1.2.0.dist-info/licenses/LICENSE
python_ember_mug-1.2.0.dist-info/RECORD
