Metadata-Version: 2.4
Name: python-ember-mug
Version: 1.2.0
Summary: Python Library for Ember Mugs.
Project-URL: Changelog, https://sopelj.github.io/python-ember-mug/changelog/
Project-URL: Documentation, https://sopelj.github.io/python-ember-mug/
Project-URL: Source code, https://github.com/sopelj/python-ember-mug/
Project-URL: Bug Tracker, https://github.com/sopelj/python-ember-mug/issues
Author-email: Jesse Sopel <jesse@sopelj.ca>
License-Expression: MIT
License-File: LICENSE
Classifier: Intended Audience :: Developers
Classifier: License :: OSI Approved :: MIT License
Classifier: Natural Language :: English
Classifier: Programming Language :: Python :: 3
Classifier: Programming Language :: Python :: 3.11
Classifier: Programming Language :: Python :: 3.12
Classifier: Programming Language :: Python :: 3.13
Requires-Python: >=3.11
Requires-Dist: bleak-retry-connector>=3.5.0
Requires-Dist: bleak>=0.22.2; python_version < '3.13'
Requires-Dist: bleak>=0.22.3; python_version <= '3.13'
Provides-Extra: dev
Requires-Dist: ipython; extra == 'dev'
Provides-Extra: docs
Requires-Dist: black; extra == 'docs'
Requires-Dist: mkdocs-autorefs; extra == 'docs'
Requires-Dist: mkdocs-gen-files; extra == 'docs'
Requires-Dist: mkdocs-include-markdown-plugin<8.0.0,>=7.0.0; extra == 'docs'
Requires-Dist: mkdocs-literate-nav; extra == 'docs'
Requires-Dist: mkdocs-material-extensions; extra == 'docs'
Requires-Dist: mkdocs-material<10.0.0,>=9.5.44; extra == 'docs'
Requires-Dist: mkdocs>=1.6.1; extra == 'docs'
Requires-Dist: mkdocstrings-python>=1.12.0; extra == 'docs'
Requires-Dist: termynal; extra == 'docs'
Provides-Extra: test
Requires-Dist: pytest-asyncio; extra == 'test'
Requires-Dist: pytest-cov; extra == 'test'
Requires-Dist: pytest>=7.2.1; extra == 'test'
